LICENSE
__init__.py
eval.py
models.py
pix2tex.py
requirements.txt
__pycache__/models.cpython-38.pyc
__pycache__/pix2tex.cpython-38.pyc
checkpoints/.gitkeep
checkpoints/weights.pth
dataset/__init__.py
dataset/arxiv.py
dataset/dataset.py
dataset/demacro.py
dataset/extract_latex.py
dataset/latex2png.py
dataset/postprocess.py
dataset/render.py
dataset/scraping.py
dataset/tokenizer.json
dataset/__pycache__/__init__.cpython-38.pyc
dataset/__pycache__/arxiv.cpython-38.pyc
dataset/__pycache__/dataset.cpython-38.pyc
dataset/__pycache__/demacro.cpython-38.pyc
dataset/__pycache__/extract_latex.cpython-38.pyc
dataset/__pycache__/latex2png.cpython-38.pyc
dataset/__pycache__/render.cpython-38.pyc
dataset/__pycache__/scraping.cpython-38.pyc
dataset/preprocessing/generate_latex_vocab.py
dataset/preprocessing/preprocess_formulas.py
dataset/preprocessing/preprocess_latex.js
dataset/preprocessing/third_party/README.md
dataset/preprocessing/third_party/katex/.#katex.js
dataset/preprocessing/third_party/katex/LICENSE.txt
dataset/preprocessing/third_party/katex/README.md
dataset/preprocessing/third_party/katex/cli.js
dataset/preprocessing/third_party/katex/katex.js
dataset/preprocessing/third_party/katex/package.json
dataset/preprocessing/third_party/katex/src/Lexer.js
dataset/preprocessing/third_party/katex/src/Options.js
dataset/preprocessing/third_party/katex/src/ParseError.js
dataset/preprocessing/third_party/katex/src/Parser.js
dataset/preprocessing/third_party/katex/src/Settings.js
dataset/preprocessing/third_party/katex/src/Style.js
dataset/preprocessing/third_party/katex/src/buildCommon.js
dataset/preprocessing/third_party/katex/src/buildHTML.js
dataset/preprocessing/third_party/katex/src/buildMathML.js
dataset/preprocessing/third_party/katex/src/buildTree.js
dataset/preprocessing/third_party/katex/src/delimiter.js
dataset/preprocessing/third_party/katex/src/domTree.js
dataset/preprocessing/third_party/katex/src/environments.js
NIA_image_2latex-1.0.dist-info/LICENSE
NIA_image_2latex-1.0.dist-info/METADATA
NIA_image_2latex-1.0.dist-info/WHEEL
NIA_image_2latex-1.0.dist-info/top_level.txt
NIA_image_2latex-1.0.dist-info/RECORD
